daspack/__init__.py
daspack/coders.py
daspack/compute.cpython-311-darwin.so
daspack/compute.pyi
daspack_dev-0.0.1a0.dist-info/METADATA
daspack_dev-0.0.1a0.dist-info/WHEEL
daspack_dev-0.0.1a0.dist-info/licenses/LICENSE
daspack_dev-0.0.1a0.dist-info/RECORD
