Metadata-Version: 2.4
Name: daspack-dev
Version: 0.0.1a0
Classifier: Programming Language :: Rust
Classifier: Programming Language :: Python :: 3
Classifier: Programming Language :: Python :: 3.8
Classifier: Programming Language :: Python :: 3.9
Classifier: Programming Language :: Python :: 3.10
Classifier: Programming Language :: Python :: 3.11
Classifier: Programming Language :: Python :: 3.12
Classifier: Programming Language :: Python :: 3.13
Classifier: Topic :: System :: Archiving :: Compression
Classifier: Intended Audience :: Science/Research
Requires-Dist: numpy>=1.24
Requires-Dist: pytest>=7 ; extra == 'test'
Provides-Extra: test
License-File: LICENSE
Summary: DASPack: Controlled data compression for Distributed Acoustic Sensing
Keywords: Distributed Acoustic Sensing,compression,Data Compression
Author: Aleix Segui
Maintainer: Aleix Segui
License: BSD-3-Clause
Requires-Python: >=3.8
Project-URL: homepage, https://aleixsegui.dev/
Project-URL: repository, https://github.com/asleix/daspack
